explainlike5/__init__.py
explainlike5/cli.py
explainlike5/llm.py
explainlike5/sample.py
explainlike5-0.1.0.dist-info/METADATA
explainlike5-0.1.0.dist-info/WHEEL
explainlike5-0.1.0.dist-info/entry_points.txt
explainlike5-0.1.0.dist-info/RECORD
