Metadata-Version: 2.3
Name: explainlike5
Version: 0.1.0
Summary: Explain or comment Python functions using LLMs like you're 5 years old.
Author: Karim
Author-email: 115158216+karimdiabb@users.noreply.github.com
Requires-Python: >=3.12
Classifier: Programming Language :: Python :: 3
Classifier: Programming Language :: Python :: 3.12
Classifier: Programming Language :: Python :: 3.13
Requires-Dist: click (>=8.2.1,<9.0.0)
Requires-Dist: openai (>=1.95.1,<2.0.0)
Requires-Dist: pytest (>=8.4.1,<9.0.0)
Requires-Dist: python-dotenv (>=1.1.1,<2.0.0)
